{"Movie": "இரண்டாம் உலகம்",
  "Lyricist": "வைரமுத்து",
  "Composer": "ஹாரிஸ்ஜெயராஜ்",
  "Song": "பல உயிர்கள் எரியும் ",
  "Year": "2012",
  "Singers": [" S. P.பாலசுப்பிரமணியம்"],
  "lyric": "பல உயிர்கள் எரியும் உடல்கள் மாரியும்பயணப்படுவது காதல்காதல் சாதல்காதல் சாதல் ரெண்டும் ஒன்று என்ன விந்தையடிஅந்த சொர்கம் போக ரெண்டும் வேண்டும் கண்ணே உண்மையடிகாதல் சாதல் ரெண்டும் ஒன்று என்ன விந்தையடிஅந்த சொர்கம் போக ரெண்டும் வேண்டுமடிஎன் காதல் தீ... தீ வாசம் நீ...கண் பார்த்தோம் வா... கை சேர்ப்போம் வா...உடல்கள் இரண்டும் சேரும் முன்உல்லம் இரண்டும் சேருமேஉடலின் வலியே உயிரை தொடுவது காதலேஇதயம் இரண்டு்ம் தூரம் தான்இதல்கள் நான்கும் அருகில் தான்இதல்கள் வலியே இதயம் தொடுவது காதலேஊசி போதும் ரெண்டு கண்களில் உயிரை குடித்தவளே நீஉயரம் காட்டும் பூக்கள் இரண்டினில் உலகம் உடைப்பவள் நீகாதல் சாதல் ரெண்டும் ஒன்று என்ன விந்தையடிஅந்த சொர்கம் போக ரெண்டும் வேண்டும் கண்ணே உண்மையடிகாதல் சாதல் ரெண்டும் ஒன்று என்ன விந்தையடிஅந்த சொர்கம் போக ரெண்டும் வேண்டுமடிஉலகில் காதல் பழையதுஉற்ற பொழுதே புதியதுஎல்லா நிலத்தும் எல்லா பொழுதும் நிகழ்வதுஉலகின் நெறுப்பு காதலேஉயிரில் இருப்பு காதலேஉண்மை காதல் உலகைவிடவும் பெரியதுகுறிஞ்சி முல்லை மருதம் நெய்தலில் குளுங்கும் பூவிதுவேபாலை வெயிலிலும் காணல் வெளியிலும் படரும் நிழில்லிதுவேகண்டார் மயங்கும் வண்டார் மலரேநின்றோர் மொழி சொல்லடிஉன் பின்னே பிறந்து முன்னே வளர்ந்துஎன்ன செழுமையடிபின்னே பிறந்து முன்னே வளர்ந்ததுஎன்ன செழுமையடிஅதை மெத்தம் எடுத்து சித்தம் துடிக்குதடிபெண் பாவாய் வா...கண் பாவாய் வா...செங்கோடாய் வா..."}